PyCNE/PyCNE.py
PyCNE/__init__.py
PyCNE-0.1.dist-info/METADATA
PyCNE-0.1.dist-info/WHEEL
PyCNE-0.1.dist-info/top_level.txt
PyCNE-0.1.dist-info/RECORD
