Metadata-Version: 2.1
Name: PyCNE
Version: 0.1
Summary: Librería que permite consultar fácilmente información del CNE (Venezuela)
Home-page: https://github.com/fckingadrien
Author: Adrián Fernández
Author-email: 48542598+fckingadrien@users.noreply.github.com
License: MIT
Platform: UNKNOWN
Requires-Dist: beautifulsoup4 (>=4.10.0)
